hex_maze_interface/__about__.py
hex_maze_interface/__init__.py
hex_maze_interface/cli.py
hex_maze_interface/hex_maze_interface.py
hex_maze_interface-4.0.0.dist-info/LICENSE
hex_maze_interface-4.0.0.dist-info/METADATA
hex_maze_interface-4.0.0.dist-info/WHEEL
hex_maze_interface-4.0.0.dist-info/entry_points.txt
hex_maze_interface-4.0.0.dist-info/top_level.txt
hex_maze_interface-4.0.0.dist-info/RECORD
