Metadata-Version: 2.1
Name: hex-maze-interface
Version: 4.0.0
Summary: Python interface to the Voigts lab hex maze.
Home-page: https://github.com/janelia-python/hex_maze_interface_python
Author: Peter Polidoro
Author-email: peter@polidoro.io
License: BSD-3-Clause
Classifier: Programming Language :: Python :: 3
License-File: LICENSE
Requires-Dist: click
Requires-Dist: python3-nmap
